jupyter_alabaster_theme/__init__.py
jupyter_alabaster_theme/custom_navigation.html
jupyter_alabaster_theme/footer.html
jupyter_alabaster_theme/layout.html
jupyter_alabaster_theme/mobile_sidebar.html
jupyter_alabaster_theme/navbar.html
jupyter_alabaster_theme/search.html
jupyter_alabaster_theme/searchbox.html
jupyter_alabaster_theme/theme.conf
jupyter_alabaster_theme/version.py
jupyter_alabaster_theme/static/index.css
jupyter_alabaster_theme/static/_images/file.svg
jupyter_alabaster_theme/static/_images/nav_logo.svg
jupyter_alabaster_theme/static/_images/search.svg
jupyter_alabaster_theme/static/_images/jupytertheme-images/breadcrumb-home.svg
jupyter_alabaster_theme/static/_images/jupytertheme-images/breadcrumb-separator.svg
jupyter_alabaster_theme/static/_images/jupytertheme-images/collapse.svg
jupyter_alabaster_theme/static/_images/jupytertheme-images/expand.svg
jupyter_alabaster_theme/static/css/bootstrap.min.css
jupyter_alabaster_theme/static/css/bootstrap.min.css.map
jupyter_alabaster_theme/static/css/jupytertheme.css
jupyter_alabaster_theme/static/js/bootstrap.js
jupyter_alabaster_theme/static/js/bootstrap.min.js
jupyter_alabaster_theme/static/js/jquery.js
jupyter_alabaster_theme/static/js/mobile-nav.js
jupyter_alabaster_theme/static/js/scroll.js
jupyter_alabaster_theme-0.3.0.dist-info/DESCRIPTION.rst
jupyter_alabaster_theme-0.3.0.dist-info/METADATA
jupyter_alabaster_theme-0.3.0.dist-info/RECORD
jupyter_alabaster_theme-0.3.0.dist-info/WHEEL
jupyter_alabaster_theme-0.3.0.dist-info/entry_points.txt
jupyter_alabaster_theme-0.3.0.dist-info/metadata.json
jupyter_alabaster_theme-0.3.0.dist-info/top_level.txt
