Metadata-Version: 2.0
Name: jupyter-alabaster-theme
Version: 0.3.0
Summary: Jupyter Alabaster Theme
Home-page: https://alabaster.readthedocs.io
Author: Jeff Forcier, Project Jupyter, and contributors
Author-email: jupyter@googlegroups.com
License: BSD
Platform: UNKNOWN
Classifier: Development Status :: 5 - Production/Stable
Classifier: Environment :: Web Environment
Classifier: Intended Audience :: Developers
Classifier: Intended Audience :: System Administrators
Classifier: License :: OSI Approved :: BSD License
Classifier: Operating System :: OS Independent
Classifier: Programming Language :: Python
Classifier: Topic :: Internet
Classifier: Topic :: Software Development :: Documentation
Requires-Dist: alabaster
Requires-Dist: setuptools
